dronefly_cli/main.py
dronefly_cli-0.2.6.dist-info/LICENSE
dronefly_cli-0.2.6.dist-info/METADATA
dronefly_cli-0.2.6.dist-info/WHEEL
dronefly_cli-0.2.6.dist-info/entry_points.txt
dronefly_cli-0.2.6.dist-info/RECORD
