Metadata-Version: 2.1
Name: dronefly-cli
Version: 0.2.6
Summary: Dronefly command-line interface
License: AGPL-3.0-or-later
Author: Ben Armstrong
Author-email: synrg@debian.org
Requires-Python: >=3.11,<3.13
Classifier: License :: OSI Approved :: GNU Affero General Public License v3 or later (AGPLv3+)
Classifier: Programming Language :: Python :: 3
Classifier: Programming Language :: Python :: 3.11
Requires-Dist: dronefly-core (==0.4.0)
Requires-Dist: pyreadline3 (>=3.4.1,<4.0.0)
Requires-Dist: rich (>=13.2,<14.0)
